kcwarden/__init__.py
kcwarden/api/__init__.py
kcwarden/api/auditor.py
kcwarden/api/monitor.py
kcwarden/auditors/__init__.py
kcwarden/auditors/client/__init__.py
kcwarden/auditors/client/client_access_token_lifespan_too_long.py
kcwarden/auditors/client/client_authentication_via_mtls_or_jwt_recommended.py
kcwarden/auditors/client/client_has_erroneously_configured_wildcard_uri.py
kcwarden/auditors/client/client_has_no_redirect_uris.py
kcwarden/auditors/client/client_has_undefined_base_domain_and_schema.py
kcwarden/auditors/client/client_must_not_use_global_wildcard_uri.py
kcwarden/auditors/client/client_must_not_use_unencrypted_nonlocal_redirect_uri.py
kcwarden/auditors/client/client_should_disable_implicit_grant_flow.py
kcwarden/auditors/client/client_should_not_use_wildcard_redirect_uri.py
kcwarden/auditors/client/client_uses_custom_redirect_uri_scheme.py
kcwarden/auditors/client/client_with_default_offline_access_scope.py
kcwarden/auditors/client/client_with_full_scope_allowed.py
kcwarden/auditors/client/client_with_optional_offline_access_scope.py
kcwarden/auditors/client/client_with_service_account_and_other_flow_enabled.py
kcwarden/auditors/client/confidential_client_should_disable_direct_access_grants.py
kcwarden/auditors/client/confidential_client_should_enforce_pkce.py
kcwarden/auditors/client/public_client_should_disable_direct_access_grants.py
kcwarden/auditors/client/public_clients_must_enforce_pkce.py
kcwarden/auditors/client/using_nondefault_user_attributes_in_clients_without_user_profiles_feature_is_dangerous.py
kcwarden/auditors/idp/__init__.py
kcwarden/auditors/idp/identity_provider_with_mappers_without_force_sync_mode.py
kcwarden/auditors/idp/identity_provider_with_one_time_sync.py
kcwarden/auditors/idp/identity_provider_with_signature_verification_disabled.py
kcwarden/auditors/idp/oidc_identity_provider_without_pkce.py
kcwarden/auditors/realm/__init__.py
kcwarden/auditors/realm/abstract_realm_auditor.py
kcwarden-0.16.0.dist-info/LICENSE
kcwarden-0.16.0.dist-info/METADATA
kcwarden-0.16.0.dist-info/WHEEL
kcwarden-0.16.0.dist-info/entry_points.txt
kcwarden-0.16.0.dist-info/RECORD
