Metadata-Version: 2.1
Name: kcwarden
Version: 0.16.0
Summary: Keycloak auditor
Home-page: https://iteratec.github.io/kcwarden/
License: Apache-2.0
Keywords: keycloak,security-scanner,oauth2,oidc
Author: Max Maass
Author-email: max.maass@iteratec.com
Requires-Python: >=3.11,<4.0
Classifier: License :: OSI Approved :: Apache Software License
Classifier: Operating System :: OS Independent
Classifier: Programming Language :: Python :: 3
Classifier: Programming Language :: Python :: 3.11
Classifier: Programming Language :: Python :: 3.12
Classifier: Topic :: Security
Classifier: Topic :: Software Development :: Testing
Requires-Dist: pyyaml (>=6.0.2,<7.0.0)
Requires-Dist: requests (>=2.32.3,<3.0.0)
Requires-Dist: rich (>=14.0.0,<15.0.0)
Project-URL: Bug Tracker, https://github.com/iteratec/kcwarden/issues
Project-URL: Documentation, https://iteratec.github.io/kcwarden/
Project-URL: Repository, https://github.com/iteratec/kcwarden
Project-URL: Sponsor, https://www.iteratec.com/
